{"LINTGED ID Equity": "Lindsell Train Global Equity F",
 "JPMEMBA LN Equity": "JPMorgan Fund ICVC - Emerging",
 "FSMEQIA LN Equity": "Fundsmith Equity Fund",
 "MNKS LN Equity": "Monks Investment Trust PLC/The",
 "BAREBIN LN Equity": "Barings UK Unit Trust Funds -",
 "CSUKBIA LN Equity": "CFP SDL UK Buffettology Fund",
 "ATT LN Equity": "Allianz Technology Trust PLC",
 "FSAPLBA LN Equity": "First State Investments ICVC-",
 "FSGEMBA LN Equity": "FS Investments ICVC- Stewart I",
 "LINTGEB ID Equity": "Lindsell Train Global Equity F",
 "LIOSSFI LN Equity": "Liontrust Special Situations F",
 "IPCBDYA LN Equity": "Invesco Perpetual Fixed Intere",
 "JOHUOYA LN Equity": "J O Hambro Capital Management"}